{"stat.chestOpened":1,"stat.walkOneCm":170896,"stat.useItem.minecraft.sapling":44,"stat.useItem.minecraft.stone":13,"stat.leaveGame":1,"stat.useItem.minecraft.golden_rail":83,"stat.useItem.minecraft.iron_block":143,"stat.useItem.minecraft.cobblestone":264,"stat.dispenserInspected":2,"stat.useItem.minecraft.rail":130,"stat.useItem.minecraft.lava_bucket":5,"stat.useItem.minecraft.dye":865,"stat.minecartOneCm":17775,"stat.useItem.minecraft.bucket":2,"stat.flyOneCm":240220,"stat.swimOneCm":70,"stat.jump":53,"stat.useItem.minecraft.minecart":1,"stat.playOneMinute":38104,"stat.useItem.minecraft.redstone":1,"stat.sneakTime":964,"stat.damageDealt":10,"stat.crouchOneCm":1720,"stat.enderchestOpened":1,"stat.timeSinceDeath":38104,"stat.useItem.minecraft.redstone_torch":9,"stat.useItem.minecraft.dirt":1,"stat.useItem.minecraft.sign":3,"stat.sprintOneCm":10630}